uqregressors/__about__.py
uqregressors/__init__.py
uqregressors/bayesian/__init__.py
uqregressors/bayesian/bbmm_gp.py
uqregressors/bayesian/deep_ens.py
uqregressors/bayesian/dropout.py
uqregressors/bayesian/gaussian_process.py
uqregressors/bayesian/temp_scaled_deep_ens.py
uqregressors/conformal/__init__.py
uqregressors/conformal/conformal_deep_ens.py
uqregressors/conformal/conformal_ens.py
uqregressors/conformal/conformal_quantile_ens.py
uqregressors/conformal/conformal_wrapper.py
uqregressors/conformal/cqr.py
uqregressors/conformal/k_fold_cqr.py
uqregressors/metrics/__init__.py
uqregressors/metrics/metrics.py
uqregressors/plotting/__init__.py
uqregressors/plotting/plotting.py
uqregressors/tuning/__init__.py
uqregressors/tuning/tuning.py
uqregressors/utils/__init__.py
uqregressors/utils/activations.py
uqregressors/utils/data_loader.py
uqregressors/utils/file_manager.py
uqregressors/utils/logging.py
uqregressors/utils/torch_sklearn_utils.py
uqregressors-1.0.8.dist-info/METADATA
uqregressors-1.0.8.dist-info/WHEEL
uqregressors-1.0.8.dist-info/licenses/LICENSE.txt
uqregressors-1.0.8.dist-info/RECORD
