Metadata-Version: 2.4
Name: uqregressors
Version: 1.0.8
Summary: PyTorch-based regressors with uncertainty quantification and scikit-learn interface
Author-email: Arjun Shah <arjunrs@stanford.edu>
License-Expression: MIT
License-File: LICENSE.txt
Requires-Python: >=3.8
Requires-Dist: gpytorch
Requires-Dist: matplotlib
Requires-Dist: numpy
Requires-Dist: openpyxl
Requires-Dist: optuna
Requires-Dist: scikit-learn
Requires-Dist: scikit-optimize
Requires-Dist: scipy
Requires-Dist: seaborn
Requires-Dist: xlrd
Provides-Extra: dev
Requires-Dist: black; extra == 'dev'
Requires-Dist: coverage; extra == 'dev'
Requires-Dist: jupyter; extra == 'dev'
Requires-Dist: mypy; extra == 'dev'
Requires-Dist: pytest; extra == 'dev'
Requires-Dist: ruff; extra == 'dev'
Provides-Extra: docs
Requires-Dist: mkdocs; extra == 'docs'
Requires-Dist: mkdocs-jupyter; extra == 'docs'
Requires-Dist: mkdocs-material; extra == 'docs'
Provides-Extra: wandb
Requires-Dist: wandb>=0.15; extra == 'wandb'
